{"name":"CreateStreamArgs","summary":"<p>Argument passed to <a href=\"/titanium-vuepress-docs/api/titanium/stream.html#createstream\">createStream</a>.</p>\n","deprecated":null,"events":[],"methods":[],"extends":"Object","properties":[{"name":"mode","deprecated":null,"summary":"<p>Mode to open the stream in.</p>\n","description":"<p>For <code>Blob</code> objects, only <code>MODE_READ</code> is supported.</p>\n","filename":"CreateStreamArgs.mode-property","platforms":[{"pretty_name":"Android","since":"1.7","name":"android"},{"pretty_name":"iPhone","since":"1.7","name":"iphone"},{"pretty_name":"iPad","since":"1.7","name":"ipad"}],"inherits":null,"examples":[],"type":"Number"},{"name":"source","deprecated":null,"summary":"<p>Object that the stream will read from or write to.</p>\n","description":null,"filename":"CreateStreamArgs.source-property","platforms":[{"pretty_name":"Android","since":"1.7","name":"android"},{"pretty_name":"iPhone","since":"1.7","name":"iphone"},{"pretty_name":"iPad","since":"1.7","name":"ipad"}],"inherits":null,"examples":[],"type":["Titanium.Blob","Titanium.Buffer"]}],"platforms":[{"pretty_name":"Android","since":"1.7","name":"android"},{"pretty_name":"iPhone","since":"1.7","name":"iphone"},{"pretty_name":"iPad","since":"1.7","name":"ipad"}],"filename":null,"type":"pseudo","subtype":null,"constants":[]}