{"name":"Titanium.Accelerometer","summary":"<p>The top-level Accelerometer module, used to determine the device's physical position.</p>\n","deprecated":null,"events":[{"name":"update","deprecated":null,"summary":"<p>Fired when the accelerometer changes.</p>\n","description":null,"filename":"Titanium.Accelerometer.update-event","platforms":[{"pretty_name":"Android","since":"0.8","name":"android"},{"pretty_name":"iPhone","since":"0.8","name":"iphone"},{"pretty_name":"iPad","since":"0.8","name":"ipad"},{"pretty_name":"Windows","since":"4.1.0","name":"windowsphone"}],"inherits":null,"properties":[{"name":"timestamp","deprecated":null,"summary":"Reference timestamp since the previous change. This is not a valid timestamp and should \nsimply be used to determine the number of milliseconds between events.\n","description":null,"type":"String","filename":"Titanium.Accelerometer.update.timestamp-callback-property"},{"name":"y","deprecated":null,"summary":"Current `y` axis of the device.","description":null,"type":"String","filename":"Titanium.Accelerometer.update.y-callback-property"},{"name":"x","deprecated":null,"summary":"Current `x` axis of the device.","description":null,"type":"String","filename":"Titanium.Accelerometer.update.x-callback-property"},{"name":"z","deprecated":null,"summary":"Current `z` axis of the device.","description":null,"type":"String","filename":"Titanium.Accelerometer.update.z-callback-property"},{"name":"bubbles","deprecated":null,"summary":"True if the event will try to bubble up if possible.","description":null,"type":"Boolean","filename":"Titanium.Accelerometer.update.bubbles-callback-property"},{"name":"cancelBubble","deprecated":null,"summary":"Set to true to stop the event from bubbling.","description":null,"type":"Boolean","filename":"Titanium.Accelerometer.update.cancelBubble-callback-property"},{"name":"source","deprecated":null,"summary":"Source object that fired the event.","description":null,"type":"Object","filename":"Titanium.Accelerometer.update.source-callback-property"},{"name":"type","deprecated":null,"summary":"Name of the event fired.","description":null,"type":"String","filename":"Titanium.Accelerometer.update.type-callback-property"}]}],"methods":[],"extends":"Titanium.Module","properties":[],"platforms":[{"pretty_name":"Android","since":"0.8","name":"android"},{"pretty_name":"iPhone","since":"0.8","name":"iphone"},{"pretty_name":"iPad","since":"0.8","name":"ipad"},{"pretty_name":"Windows","since":"4.1.0","name":"windowsphone"}],"filename":null,"type":"module","subtype":null,"constants":[]}